remote_minerl_env/__init__.py
remote_minerl_env/cli.py
remote_minerl_env/proto.py
remote_minerl_env/environments/__init__.py
remote_minerl_env/environments/client.py
remote_minerl_env/environments/server.py
remote_minerl_env/sock/__init__.py
remote_minerl_env/sock/socket.py
remote_minerl_env-0.1.dist-info/METADATA
remote_minerl_env-0.1.dist-info/WHEEL
remote_minerl_env-0.1.dist-info/entry_points.txt
remote_minerl_env-0.1.dist-info/top_level.txt
remote_minerl_env-0.1.dist-info/RECORD
