Metadata-Version: 2.1
Name: remote-minerl-env
Version: 0.1
Summary: Remote environment for minerl competition environments
Home-page: https://github.com/infinityofspace/remote_minerl_env
Author: infinityofspace
License: MIT
Platform: UNKNOWN
Classifier: Development Status :: 4 - Beta
Classifier: Programming Language :: Python :: 3
Classifier: Programming Language :: Python :: 3.6
Classifier: Programming Language :: Python :: 3.7
Classifier: Programming Language :: Python :: 3.8
Classifier: Programming Language :: Python :: 3.9
Classifier: License :: OSI Approved :: MIT License
Classifier: Topic :: Utilities
Requires-Python: >=3.6
Requires-Dist: minerl (>=0.3.6)
Requires-Dist: pyngrok (>=5.1.0)
